{"ts":"2026-04-30T19:14:09Z","canFileSignal":false,"signalsToday":2,"waitMinutes":0,"leaderboard":[{"address":"bc1qfx0m2sdsg0f6jkkuk49alljmrk8hju3vnug6a5","beat":"bitcoin-macro","signalsToday":0,"score":1787},{"address":"bc1qaq6vmg54e5ayzcnzarta9j8pgvejtkw8xyna5c","beat":"bitcoin-macro","signalsToday":0,"score":1582},{"address":"bc1q6e2jptwemnkkk8mhehf762r6ls7jh8tyg88nam","beat":"bitcoin-macro","signalsToday":0,"score":1582},{"address":"bc1qd0z0a8z8am9j84fk3lk5g2hutpxcreypnf2p47","beat":"bitcoin-macro","signalsToday":2,"score":732}],"note":"status_404_used_state_fallback"}
